{
  "champions": [
    {
      "id": "champion-001",
      "name": "Stephen Hlotyak",
      "email": "stephen.hlotyak@teradyne.com",
      "division": "Semiconductor Test",
      "businessUnits": ["compute-test"],
      "focusArea": "Engineering - Software",
      "timeCommitmentPct": 30,
      "headcountCovered": 97,
      "status": "confirmed",
      "appointmentDate": "2026-01-21",
      "productLines": ["UltraFlex", "J750", "T2000", "IG-XL"],
      "notes": "Covers Compute Test Engineering - Software (97 employees, 100% coverage)."
    },
    {
      "id": "champion-002",
      "name": "Jacob Pilegaard",
      "email": "japi@universal-robots.com",
      "division": "Robotics",
      "businessUnits": ["ur", "mir"],
      "focusArea": "Engineering - Software",
      "headcountCovered": 78,
      "status": "confirmed",
      "appointmentDate": "2026-01-21",
      "notes": "Covers UR + MiR Engineering - Software (78 employees, 100% coverage)."
    },
    {
      "id": "champion-003",
      "name": "Martin Nordentoft",
      "email": "martin.nordentoft@teradyne-robotics.com",
      "division": "Corporate",
      "focusArea": "IT",
      "headcountCovered": 139,
      "status": "confirmed",
      "appointmentDate": "2026-01-21",
      "notes": "Covers corporate IT function (139 employees, 100% coverage)."
    },
    {
      "id": "champion-004",
      "name": "Fleur Nielsen",
      "email": "flni@universal-robots.com",
      "division": "Robotics",
      "focusArea": "Marketing",
      "headcountCovered": 37,
      "status": "pending",
      "notes": "Covers Robotics Marketing division-level function (37 employees, 100% coverage)."
    }
  ],
  "metadata": {
    "lastUpdated": "2026-01-25",
    "note": "totalOrg and coveragePercentage are now calculated dynamically from live CDN data. headcountCovered values updated to match actual org hierarchy function headcounts (100% of assigned function).",
    "totalCoveredByConfirmedChampions": 314,
    "coverageBreakdown": {
      "stephen-hlotyak": "97 (Semiconductor Test > Compute Test > Engineering - Software)",
      "jacob-pilegaard": "78 (Robotics > UR+MiR > Engineering - Software)",
      "martin-nordentoft": "139 (Corporate > IT)"
    }
  }
}
